CHANGES.rst
stylo/__init__.py
stylo/_version.py
stylo/color/__init__.py
stylo/color/colormap.py
stylo/color/colorspaces.py
stylo/color/fill.py
stylo/design/__init__.py
stylo/design/_param_factory.py
stylo/design/params.py
stylo/domain/__init__.py
stylo/domain/_factory.py
stylo/domain/helpers.py
stylo/domain/rectangular.py
stylo/domain/square.py
stylo/domain/transform/__init__.py
stylo/domain/transform/rotation.py
stylo/domain/transform/shear.py
stylo/domain/transform/transform.py
stylo/domain/transform/translation.py
stylo/error.py
stylo/image/__init__.py
stylo/image/image.py
stylo/image/layered.py
stylo/image/simple.py
stylo/math/__init__.py
stylo/math/interpolation.py
stylo/math/logic.py
stylo/shape/__init__.py
stylo/shape/basic.py
stylo/shape/curves.py
stylo/shape/shape.py
stylo/testing/__init__.py
stylo/testing/_domain_factory.py
stylo/testing/_param_factory.py
stylo/testing/color.py
stylo/testing/design.py
stylo/testing/domain.py
stylo/testing/image.py
stylo/testing/shape.py
stylo/testing/strategies.py
stylo/time/__init__.py
stylo/time/clock.py
stylo/time/event.py
stylo/time/timeline.py
stylo/utils.py
stylo-0.9.3.dist-info/LICENSE
stylo-0.9.3.dist-info/WHEEL
stylo-0.9.3.dist-info/METADATA
stylo-0.9.3.dist-info/RECORD
